[
    {
        "name": "Pawan Majhi",
        "email": "majhipawan27@gmail.com"
    },
    {
        "name": "Buwan Khatri",
        "email": "bhuwankhatri9827@gmail.com"
    },
    {
        "name": "Bipana Goutam",
        "email": "goutambipana@gmail.com",
        "phone": "9810437481"
    },
    {
        "name": "Bibhusan Shrestha",
        "email": "bibhusansth1@gmail.com",
        "phone": "9749922446"
    },
    {
        "name": "Romila Rai",
        "email": "thimrangromila@gmail.com",
        "phone": "9761635190"
    },
    {
        "name": "Sanjita Rai",
        "email": "ssanjitarai189@gmail.com",
        "phone": "9741890541"
    },
    {
        "name": "Sakuntala Thapa",
        "email": "tapasakuntala6@gmail.com",
        "phone": "9827337646"
    },
    {
        "name": "Amar Rai",
        "email": "rayeeamar@gmail.com",
        "phone": "9840986664"
    },
    {
        "name": "Renuka Basnet",
        "email": "renukabasnet810@gmail.com",
        "phone": "9861740168"
    },
    {
        "name": "Puja Tamang",
        "email": "tamangpooja271@gmail.com",
        "phone": "9862115185"
    },
    {
        "name": "Saraswati Tamang",
        "email": "saraswati60012@gmail.com",
        "phone": "9762216001"
    },
    {
        "name": "Saugat Gautam",
        "email": "saugatstruggle2049@gmail.com",
        "phone": "9842043618"
    },
    {
        "name": "Kalpana Luitel",
        "email": "kalpanaluitel9845@gmail.com",
        "phone": "9845263677"
    },
    {
        "name": "Nirmala Karki",
        "email": "karkinirmala813@gmail.com",
        "phone": "9843004160"
    },
    {
        "name": "Kalawati Bohara",
        "email": "kalawatibohara53@gmail.com",
        "phone": "9843981154"
    },
    {
        "name": "Jeni Kala Rai",
        "email": "jennysampang1995@gmail.com",
        "phone": "9746227745"
    },
    {
        "name": "Jaya Rai",
        "email": "jr7700145@gmail.com",
        "phone": "9840652462"
    },
    {
        "name": "Rahul Kumar Chaudhary",
        "email": "chaudharyrahul14632@gmail.com",
        "phone": "9746673046"
    },
    {
        "name": "Ashika Rai",
        "email": "aashikarai527@gmail.com",
        "phone": "9761635066"
    },
    {
        "name": "Susmita Khatri",
        "email": "susmitadahalkhatri05@gmail.com",
        "phone": "9842477756"
    },
    {
        "name": "Anjuli Tamang",
        "email": "tamanganjuli120@gmail.com",
        "phone": "9842456674"
    },
    {
        "name": "Asmita Karki",
        "email": "asmitakarki2006@gmail.com",
        "phone": "9766856440"
    },
    {
        "name": "Laxmi Tamang",
        "email": "laxmitmg2052@gmail.com",
        "phone": "9846839393"
    },
    {
        "name": "Anusa Basnet",
        "email": "basnetanisha363@gmail.com",
        "phone": "9767772906"
    },
    {
        "name": "Surjana Khadka",
        "email": "kadkasrizaana987@gmail.com",
        "phone": "9860855295"
    },
    {
        "name": "Biddya Kuikel",
        "email": "biddyakikel175@gmail.com",
        "phone": "9848062918"
    },
    {
        "name": "Pramila Karki",
        "email": "pk.karki900@gmail.com"
    },
    {
        "name": "Nayan Bhattarai",
        "email": "nayanbhattarai21@gmail.com",
        "phone": "9860806634"
    },
    {
        "name": "Sunita Basnet",
        "email": "sunitabasnet146@gmail.com",
        "phone": "9864698636"
    },
    {
        "name": "Mangal Darnal",
        "email": "darnalmangal@gmail.com",
        "phone": "9848454527"
    },
    {
        "name": "Krishla Bista",
        "email": "bistakrishala215@gmail.com",
        "phone": "9765467315"
    },
    {
        "name": "Yamuna Bayalkoti",
        "email": "yamunabayalkoti937@gmail.com",
        "phone": "9814320847"
    },
    {
        "name": "Anjali Lohar",
        "email": "anjalilohar523@gmail.com",
        "phone": "9761878818"
    },
    {
        "name": "Sabita Shrestha",
        "email": "sabitashrestha2060@gmail.com",
        "phone": "9840036799"
    },
    {
        "name": "Rojina Hingmang",
        "email": "rojinahingmang829@gmail.com"
    },
    {
        "name": "Nikhilesh Koirala",
        "email": "nikhileshkoirala55@gmail.com"
    },
    {
        "name": "Ratnadhan Rai",
        "email": "ratbadhanrai987@gmail.com",
        "phone": "9847795797"
    },
    {
        "name": "Ranjana Khatri",
        "email": "ranjanakhatri08@gmail.com",
        "phone": "9745957346"
    }
]
